invase/__init__.py
invase/logger.py
invase/method.py
invase/version.py
invase/utils/__init__.py
invase/utils/distributions.py
invase-0.0.3.dist-info/LICENSE
invase-0.0.3.dist-info/METADATA
invase-0.0.3.dist-info/WHEEL
invase-0.0.3.dist-info/top_level.txt
invase-0.0.3.dist-info/RECORD
