Metadata-Version: 2.1
Name: invase
Version: 0.0.3
Summary: INVASE: Instance-wise Variable Selection
Home-page: https://www.vanderschaar-lab.com/
Author: vanderschaarlab
Author-email: 
License: MIT
Project-URL: Twitter, https://twitter.com/MihaelaVDS
Platform: any
Classifier: Programming Language :: Python :: 3
Classifier: Topic :: Scientific/Engineering :: Artificial Intelligence
Classifier: Intended Audience :: Science/Research
Classifier: License :: OSI Approved :: MIT License
Classifier: Operating System :: OS Independent
License-File: LICENSE
Requires-Dist: scikit-learn (>=1.0)
Requires-Dist: pandas (>=1.3)
Requires-Dist: torch (>=1.10.0)
Requires-Dist: numpy (>=1.20)
Requires-Dist: loguru
Requires-Dist: pydantic
Requires-Dist: cloudpickle
Requires-Dist: scipy
Requires-Dist: matplotlib
Requires-Dist: seaborn
Requires-Dist: importlib-metadata ; python_version < "3.8"
Provides-Extra: testing
Requires-Dist: pre-commit ; extra == 'testing'
Requires-Dist: setuptools ; extra == 'testing'
Requires-Dist: pytest ; extra == 'testing'
Requires-Dist: pytest-cov ; extra == 'testing'
Requires-Dist: bandit ; extra == 'testing'
Requires-Dist: jupyter ; extra == 'testing'
Requires-Dist: notebook ; extra == 'testing'
